writ
