Metadata-Version: 2.1
Name: writ
Version: 0.1.5
Summary: A source file creation tool.
Home-page: UNKNOWN
Author: jacksonelfers
Author-email: JacksonElfers@hotmail.com
License: Creative Commons Attribution-Noncommercial-Share Alike license
Platform: UNKNOWN
